perfect404/__init__.py
perfect404/views.py
perfect404/templates/perfect404.html
scripts/__init__.py
scripts/releaser_hooks.py
django_perfect404-1.2.dist-info/LICENSE.txt
django_perfect404-1.2.dist-info/METADATA
django_perfect404-1.2.dist-info/WHEEL
django_perfect404-1.2.dist-info/top_level.txt
django_perfect404-1.2.dist-info/zip-safe
django_perfect404-1.2.dist-info/RECORD
